diffraxtra/__init__.py
diffraxtra/_version.py
diffraxtra/_version.pyi
diffraxtra/py.typed
diffraxtra/_src/__init__.py
diffraxtra/_src/diffeq.py
diffraxtra/_src/diffeq_abc.py
diffraxtra/_src/interp.py
diffraxtra-1.5.2.dist-info/METADATA
diffraxtra-1.5.2.dist-info/WHEEL
diffraxtra-1.5.2.dist-info/licenses/LICENSE
diffraxtra-1.5.2.dist-info/RECORD
