Metadata-Version: 2.4
Name: diffraxtra
Version: 1.5.2
Summary: diffrax extras: OOP and vectorization
Project-URL: Homepage, https://github.com/GalacticDynamics/diffraxtra
Project-URL: Bug Tracker, https://github.com/GalacticDynamics/diffraxtra/issues
Project-URL: Discussions, https://github.com/GalacticDynamics/diffraxtra/discussions
Project-URL: Changelog, https://github.com/GalacticDynamics/diffraxtra/releases
Author-email: Nathaniel Starkman <nstarman@users.noreply.github.com>
License: Copyright 2024 Nathaniel Starkman
License-File: LICENSE
Classifier: Development Status :: 1 - Planning
Classifier: Intended Audience :: Developers
Classifier: Intended Audience :: Science/Research
Classifier: License :: OSI Approved :: MIT License
Classifier: Operating System :: OS Independent
Classifier: Programming Language :: Python
Classifier: Programming Language :: Python :: 3
Classifier: Programming Language :: Python :: 3 :: Only
Classifier: Programming Language :: Python :: 3.11
Classifier: Programming Language :: Python :: 3.12
Classifier: Programming Language :: Python :: 3.13
Classifier: Topic :: Scientific/Engineering
Classifier: Typing :: Typed
Requires-Python: >=3.11
Requires-Dist: diffrax>=0.6
Requires-Dist: equinox>=0.11.5
Requires-Dist: jaxtyping>=0.2.35
Requires-Dist: plum-dispatch>=2.5.7
Requires-Dist: typing-extensions>=4.12.2
